automaited/__init__.py
automaited/_doc_ext_client.py
automaited/py.typed
automaited-0.1.4.dist-info/METADATA
automaited-0.1.4.dist-info/WHEEL
automaited-0.1.4.dist-info/licenses/LICENSE
automaited-0.1.4.dist-info/RECORD
